{"version":3,"kind":"Notebook","sha256":"00b6cc940c808ffe81e7f4b6f724347663d99d64de40683904006bf7adf296d3","slug":"notebooks.ptype-ml","location":"/notebooks/ptype_ml.ipynb","dependencies":[],"frontmatter":{"title":"Regression ML Analysis - Atmospheric Data Quick Start","content_includes_title":false,"kernelspec":{"name":"python3","display_name":"Python 3 (ipykernel)","language":"python"},"authors":[{"nameParsed":{"literal":"Project Pythia Community","given":"Project Pythia","family":"Community"},"name":"Project Pythia Community","url":"https://projectpythia.org/","id":"contributors-myst-generated-uid-0"}],"open_access":true,"license":{"content":{"id":"CC-BY-4.0","url":"https://creativecommons.org/licenses/by/4.0/","name":"Creative Commons Attribution 4.0 International","free":true,"CC":true},"code":{"id":"Apache-2.0","url":"https://opensource.org/licenses/Apache-2.0","name":"Apache License 2.0","free":true,"osi":true}},"github":"https://github.com/projectpythia/ptype-ml-cookbook","copyright":"2024","affiliations":[{"id":"UAlbany","name":"University at Albany (SUNY)","department":"Atmospheric and Environmental Sciences","url":"https://www.albany.edu/daes"},{"id":"CISL","name":"NSF National Center for Atmospheric Research","department":"Computational and Information Systems Lab","url":"https://www.cisl.ucar.edu"},{"id":"Unidata","name":"NSF Unidata","url":"https://www.unidata.ucar.edu"},{"id":"Argonne","name":"Argonne National Laboratory","department":"Environmental Science Division","url":"https://www.anl.gov/evs"},{"id":"CarbonPlan","name":"CarbonPlan","url":"https://carbonplan.org"},{"id":"NVIDIA","name":"NVIDIA Corporation","url":"https://www.nvidia.com/"}],"numbering":{"title":{"offset":1}},"source_url":"https://github.com/projectpythia/ptype-ml-cookbook/blob/main/notebooks/ptype_ml.ipynb","edit_url":"https://github.com/projectpythia/ptype-ml-cookbook/edit/main/notebooks/ptype_ml.ipynb","exports":[{"format":"ipynb","filename":"ptype_ml.ipynb","url":"/ptype-ml-cookbook/build/ptype_ml-eb25404ca9fe5561da73387abd4da173.ipynb"}]},"widgets":{},"mdast":{"type":"root","children":[{"type":"block","kind":"notebook-content","children":[{"type":"thematicBreak","position":{"start":{"line":1,"column":1},"end":{"line":1,"column":1}},"key":"vSqdYJspsl"}],"key":"cz1aHjWAhu"},{"type":"block","kind":"notebook-content","children":[{"type":"heading","depth":2,"position":{"start":{"line":1,"column":1},"end":{"line":1,"column":1}},"children":[{"type":"text","value":"Overview","position":{"start":{"line":1,"column":1},"end":{"line":1,"column":1}},"key":"PWUTAGFh5a"}],"identifier":"overview","label":"Overview","html_id":"overview","implicit":true,"key":"W6NscjpGBk"},{"type":"paragraph","position":{"start":{"line":2,"column":1},"end":{"line":2,"column":1}},"children":[{"type":"text","value":"In this cookbook we will go through a simple example showing the Supervised Machine Learning Regression Framework, using the ","position":{"start":{"line":2,"column":1},"end":{"line":2,"column":1}},"key":"PiY4J9xG4T"},{"type":"link","url":"https://scikit-learn.org/stable/","position":{"start":{"line":2,"column":1},"end":{"line":2,"column":1}},"children":[{"type":"text","value":"scikit-learn","position":{"start":{"line":2,"column":1},"end":{"line":2,"column":1}},"key":"JMAbOMueKI"}],"urlSource":"https://scikit-learn.org/stable/","key":"wDUr40hfB2"},{"type":"text","value":" ecosystem.","position":{"start":{"line":2,"column":1},"end":{"line":2,"column":1}},"key":"GI5XsnBIeS"}],"key":"CUSTHjeOrP"},{"type":"list","ordered":true,"start":1,"spread":false,"position":{"start":{"line":4,"column":1},"end":{"line":7,"column":1}},"children":[{"type":"listItem","spread":true,"position":{"start":{"line":4,"column":1},"end":{"line":4,"column":1}},"children":[{"type":"paragraph","children":[{"type":"text","value":"Reading Data and Exploratory Data Analysis","position":{"start":{"line":4,"column":1},"end":{"line":4,"column":1}},"key":"ZJqP7hSXMb"}],"key":"nbyzxKD82C"}],"key":"M3Z47nzr2d"},{"type":"listItem","spread":true,"position":{"start":{"line":5,"column":1},"end":{"line":5,"column":1}},"children":[{"type":"paragraph","children":[{"type":"text","value":"Splitting Dataset and Scaling Data","position":{"start":{"line":5,"column":1},"end":{"line":5,"column":1}},"key":"tizrQqJPva"}],"key":"Ay109KSneJ"}],"key":"wdS7wQEyiX"},{"type":"listItem","spread":true,"position":{"start":{"line":6,"column":1},"end":{"line":7,"column":1}},"children":[{"type":"paragraph","children":[{"type":"text","value":"Training, Testing, and Validating Model","position":{"start":{"line":6,"column":1},"end":{"line":6,"column":1}},"key":"AzeygZ3G0J"}],"key":"GVDzcE4TJm"}],"key":"VnKJKN5vNj"}],"key":"GlDeHst2Rg"},{"type":"paragraph","position":{"start":{"line":8,"column":1},"end":{"line":8,"column":1}},"children":[{"type":"text","value":"This is a MVP (or minimum viable product) for ML modeling analysis. There are many more things we could test and add to this. The dataset itself is also very small for fast loading and general speed. This CookBook is meant to be a companion to ","position":{"start":{"line":8,"column":1},"end":{"line":8,"column":1}},"key":"VxRL7QZ2bt"},{"type":"link","url":"https://www.unidata.ucar.edu/","position":{"start":{"line":8,"column":1},"end":{"line":8,"column":1}},"children":[{"type":"text","value":"Unidata’s","position":{"start":{"line":8,"column":1},"end":{"line":8,"column":1}},"key":"RdujjT7DUT"}],"urlSource":"https://www.unidata.ucar.edu/","key":"Y2CtPFjPmE"},{"type":"text","value":" Cybertraining project.","position":{"start":{"line":8,"column":1},"end":{"line":8,"column":1}},"key":"WWRmOFWuKU"}],"key":"kUrFUlM5G4"}],"key":"s1VU8OFQ88"},{"type":"block","kind":"notebook-content","children":[{"type":"heading","depth":2,"position":{"start":{"line":1,"column":1},"end":{"line":1,"column":1}},"children":[{"type":"text","value":"Prerequisites","position":{"start":{"line":1,"column":1},"end":{"line":1,"column":1}},"key":"mKsEkDbwoa"}],"identifier":"prerequisites","label":"Prerequisites","html_id":"prerequisites","implicit":true,"key":"u2uwE8ccit"},{"type":"table","position":{"start":{"line":5,"column":1},"end":{"line":10,"column":1}},"children":[{"type":"tableRow","position":{"start":{"line":5,"column":1},"end":{"line":5,"column":1}},"children":[{"type":"tableCell","header":true,"position":{"start":{"line":5,"column":1},"end":{"line":5,"column":1}},"children":[{"type":"text","value":"Concepts","position":{"start":{"line":5,"column":1},"end":{"line":5,"column":1}},"key":"b3608Fr9eD"}],"key":"eLsUssL3b9"},{"type":"tableCell","header":true,"position":{"start":{"line":5,"column":1},"end":{"line":5,"column":1}},"children":[{"type":"text","value":"Importance","position":{"start":{"line":5,"column":1},"end":{"line":5,"column":1}},"key":"WldDrXXtaX"}],"key":"RFmJbaitTN"},{"type":"tableCell","header":true,"position":{"start":{"line":5,"column":1},"end":{"line":5,"column":1}},"children":[{"type":"text","value":"Notes","position":{"start":{"line":5,"column":1},"end":{"line":5,"column":1}},"key":"gQPwrmwCrk"}],"key":"wGoSs8BTrN"}],"key":"iFLS8rc7kJ"},{"type":"tableRow","position":{"start":{"line":7,"column":1},"end":{"line":7,"column":1}},"children":[{"type":"tableCell","position":{"start":{"line":7,"column":1},"end":{"line":7,"column":1}},"children":[{"type":"link","url":"https://elearning.unidata.ucar.edu/dataeLearning/Cybertraining/foundations/","position":{"start":{"line":7,"column":1},"end":{"line":7,"column":1}},"children":[{"type":"text","value":"Machine Learning Foundations in the Earth Systems Sciences","position":{"start":{"line":7,"column":1},"end":{"line":7,"column":1}},"key":"aIML4RkHrK"}],"urlSource":"https://elearning.unidata.ucar.edu/dataeLearning/Cybertraining/foundations/","key":"LsRAZz4c9j"}],"key":"PVPu3Y3K4O"},{"type":"tableCell","position":{"start":{"line":7,"column":1},"end":{"line":7,"column":1}},"children":[{"type":"text","value":"Necessary","position":{"start":{"line":7,"column":1},"end":{"line":7,"column":1}},"key":"uRGLGZj3ai"}],"key":"lFaCHwgCz3"},{"type":"tableCell","position":{"start":{"line":7,"column":1},"end":{"line":7,"column":1}},"children":[],"key":"tdeOjdRSPo"}],"key":"tBBEEMlfIm"},{"type":"tableRow","position":{"start":{"line":8,"column":1},"end":{"line":8,"column":1}},"children":[{"type":"tableCell","position":{"start":{"line":8,"column":1},"end":{"line":8,"column":1}},"children":[{"type":"link","url":"https://pandas.pydata.org/docs/user_guide/10min.html","position":{"start":{"line":8,"column":1},"end":{"line":8,"column":1}},"children":[{"type":"text","value":"10 minutes to pandas","position":{"start":{"line":8,"column":1},"end":{"line":8,"column":1}},"key":"rO5wi1y6pG"}],"urlSource":"https://pandas.pydata.org/docs/user_guide/10min.html","key":"tjaqR6Qtm9"}],"key":"Cu8mNXQU3N"},{"type":"tableCell","position":{"start":{"line":8,"column":1},"end":{"line":8,"column":1}},"children":[{"type":"text","value":"Necessary","position":{"start":{"line":8,"column":1},"end":{"line":8,"column":1}},"key":"IJDFN3LGXa"}],"key":"gb6pVXPnvt"},{"type":"tableCell","position":{"start":{"line":8,"column":1},"end":{"line":8,"column":1}},"children":[],"key":"y8ABuVHzoM"}],"key":"SBjjoSOrjL"},{"type":"tableRow","position":{"start":{"line":9,"column":1},"end":{"line":9,"column":1}},"children":[{"type":"tableCell","position":{"start":{"line":9,"column":1},"end":{"line":9,"column":1}},"children":[{"type":"link","url":"https://matplotlib.org/stable/tutorials/pyplot.html","position":{"start":{"line":9,"column":1},"end":{"line":9,"column":1}},"children":[{"type":"text","value":"Pyplot tutorial","position":{"start":{"line":9,"column":1},"end":{"line":9,"column":1}},"key":"cBrQpodRKn"}],"urlSource":"https://matplotlib.org/stable/tutorials/pyplot.html","key":"uN7IEPo9Dx"}],"key":"dVLp1jLXLv"},{"type":"tableCell","position":{"start":{"line":9,"column":1},"end":{"line":9,"column":1}},"children":[{"type":"text","value":"Helpful","position":{"start":{"line":9,"column":1},"end":{"line":9,"column":1}},"key":"AiCn1F7tqn"}],"key":"cRSCV3VOcU"},{"type":"tableCell","position":{"start":{"line":9,"column":1},"end":{"line":9,"column":1}},"children":[{"type":"text","value":"Necessary","position":{"start":{"line":9,"column":1},"end":{"line":9,"column":1}},"key":"bIRRA9KpwZ"}],"key":"ni7loxbfkZ"}],"key":"bbNsBr9pLX"},{"type":"tableRow","position":{"start":{"line":10,"column":1},"end":{"line":10,"column":1}},"children":[{"type":"tableCell","position":{"start":{"line":10,"column":1},"end":{"line":10,"column":1}},"children":[{"type":"link","url":"https://numpy.org/doc/stable/user/absolute_beginners.html","position":{"start":{"line":10,"column":1},"end":{"line":10,"column":1}},"children":[{"type":"text","value":"Numpy: the absolute basics for beginners","position":{"start":{"line":10,"column":1},"end":{"line":10,"column":1}},"key":"WaeU7AMbaI"}],"urlSource":"https://numpy.org/doc/stable/user/absolute_beginners.html","key":"PR9W4pO0Yx"}],"key":"f0l3W9cWPU"},{"type":"tableCell","position":{"start":{"line":10,"column":1},"end":{"line":10,"column":1}},"children":[{"type":"text","value":"Great to have","position":{"start":{"line":10,"column":1},"end":{"line":10,"column":1}},"key":"lITuCWF2GK"}],"key":"Asx5euUBzV"},{"type":"tableCell","position":{"start":{"line":10,"column":1},"end":{"line":10,"column":1}},"children":[{"type":"text","value":"arrays are the language of machine learning","position":{"start":{"line":10,"column":1},"end":{"line":10,"column":1}},"key":"AbtFsD3Na1"}],"key":"lsah1irSTi"}],"key":"tGfkASoZz5"}],"key":"UfMiIRxytg"},{"type":"list","ordered":false,"spread":false,"position":{"start":{"line":12,"column":1},"end":{"line":13,"column":1}},"children":[{"type":"listItem","spread":true,"position":{"start":{"line":12,"column":1},"end":{"line":13,"column":1}},"children":[{"type":"paragraph","children":[{"type":"strong","position":{"start":{"line":12,"column":1},"end":{"line":12,"column":1}},"children":[{"type":"text","value":"Time to learn","position":{"start":{"line":12,"column":1},"end":{"line":12,"column":1}},"key":"ipXJfNJyFn"}],"key":"IZTAJLWk4a"},{"type":"text","value":": 45 minutes","position":{"start":{"line":12,"column":1},"end":{"line":12,"column":1}},"key":"O4X8vbanwk"}],"key":"uKVVK5cTxg"}],"key":"fYGeBjqeP1"}],"key":"DBtOgffVQp"},{"type":"paragraph","position":{"start":{"line":14,"column":1},"end":{"line":14,"column":1}},"children":[{"type":"text","value":"While it can be easy to get started with the scikit learn syntax, it can take a while to fully understand and learn all of the in’s and out’s of ML systems. This is designed to just be a very quick introduction.","position":{"start":{"line":14,"column":1},"end":{"line":14,"column":1}},"key":"gEmrusswcn"}],"key":"fmZ6euW15K"}],"key":"quGUl8au0A"},{"type":"block","kind":"notebook-content","children":[{"type":"thematicBreak","position":{"start":{"line":1,"column":1},"end":{"line":1,"column":1}},"key":"p0ncYQSM3L"}],"key":"nxdjA5cTEi"},{"type":"block","kind":"notebook-content","children":[{"type":"heading","depth":2,"position":{"start":{"line":1,"column":1},"end":{"line":1,"column":1}},"children":[{"type":"text","value":"Imports","position":{"start":{"line":1,"column":1},"end":{"line":1,"column":1}},"key":"P823TA0eHY"}],"identifier":"imports","label":"Imports","html_id":"imports","implicit":true,"key":"tzH4qK9rrx"}],"key":"vb3cnixwb2"},{"type":"block","kind":"notebook-content","children":[{"type":"paragraph","position":{"start":{"line":1,"column":1},"end":{"line":1,"column":1}},"children":[{"type":"text","value":"Uncomment the below line if you need to install the packages below","position":{"start":{"line":1,"column":1},"end":{"line":1,"column":1}},"key":"j4DDZsrKkR"}],"key":"SCIm2GRwqI"}],"key":"xLgdebgii0"},{"type":"block","kind":"notebook-code","children":[{"type":"code","lang":"python","executable":true,"value":"# pip install numpy pandas seaborn matplotlib pyarrow","key":"twkojVqcOi"},{"type":"outputs","id":"hf8v5b7OGRbw29vIP0jPE","children":[],"key":"tZuJIPKqYl"}],"key":"tZopygAwMa"},{"type":"block","kind":"notebook-code","children":[{"type":"code","lang":"python","executable":true,"value":"import numpy as np\nimport pandas as pd\n\nimport seaborn as sns\nimport matplotlib.pyplot as plt\n\n# needed to read in parquet files\nimport pyarrow","key":"YlpHaRn0Fg"},{"type":"outputs","id":"q_AoG7hlGT5r95JCvtDPk","children":[],"key":"WVR7BEnZDy"}],"key":"rVg1loLhOh"},{"type":"block","kind":"notebook-content","children":[{"type":"paragraph","position":{"start":{"line":1,"column":1},"end":{"line":1,"column":1}},"children":[{"type":"text","value":"We will do more imports as they come in the notebook.","position":{"start":{"line":1,"column":1},"end":{"line":1,"column":1}},"key":"zbxRUPO4uL"}],"key":"urXlw2WjMY"}],"key":"atyoEbUzi6"},{"type":"block","kind":"notebook-content","children":[{"type":"heading","depth":2,"position":{"start":{"line":1,"column":1},"end":{"line":1,"column":1}},"children":[{"type":"text","value":"Read in the data","position":{"start":{"line":1,"column":1},"end":{"line":1,"column":1}},"key":"c8MFd0BM4u"}],"identifier":"read-in-the-data","label":"Read in the data","html_id":"read-in-the-data","implicit":true,"key":"H1l03rrsP1"}],"key":"aM8nJLcl1Q"},{"type":"block","kind":"notebook-content","children":[{"type":"paragraph","position":{"start":{"line":1,"column":1},"end":{"line":1,"column":1}},"children":[{"type":"text","value":"First we will read our data file and examine it’s size. We can also read csv files using the ","position":{"start":{"line":1,"column":1},"end":{"line":1,"column":1}},"key":"zmJbAyfwlh"},{"type":"inlineCode","value":"read_csv()","position":{"start":{"line":1,"column":1},"end":{"line":1,"column":1}},"key":"g2CVVweuA7"},{"type":"text","value":" function from pandas.","position":{"start":{"line":1,"column":1},"end":{"line":1,"column":1}},"key":"k2JqucZHbW"}],"key":"qmyrcKZCq5"}],"key":"JuqANrtK5z"},{"type":"block","kind":"notebook-code","children":[{"type":"code","lang":"python","executable":true,"value":"df = pd.read_parquet(r'../0_data/ptype_sampled.parquet')","key":"dtbSnEWzfo"},{"type":"outputs","id":"4n3ugFrZTM9aNzpmHMGBl","children":[],"key":"OAdRXcR1FY"}],"key":"wv2RkWMH4l"},{"type":"block","kind":"notebook-code","children":[{"type":"code","lang":"python","executable":true,"value":"memory_in_megabytes = df.memory_usage(deep=True).sum() / (1024 ** 2)\nprint(f\"The DataFrame size is: {memory_in_megabytes:.2f} MB\")\n\nprint('The shape of the Dataframe is ' + str(df.shape))","key":"UdgyTDVx5o"},{"type":"outputs","id":"8Dhhy-R0QJEQdey5krLga","children":[{"type":"output","children":[],"jupyter_data":{"output_type":"stream","name":"stdout","text":"The DataFrame size is: 0.06 MB\nThe shape of the Dataframe is (2000, 6)\n"},"key":"iC4ZzA2aUH"}],"key":"WZWFggdU81"}],"key":"H5oujX9QKU"},{"type":"block","kind":"notebook-content","children":[{"type":"paragraph","position":{"start":{"line":1,"column":1},"end":{"line":1,"column":1}},"children":[{"type":"text","value":"So we have 2000 rows, and 6 columns","position":{"start":{"line":1,"column":1},"end":{"line":1,"column":1}},"key":"pikoAXxAKh"}],"key":"wiKG1X68IV"}],"key":"v3xf1jmE0d"},{"type":"block","kind":"notebook-content","children":[{"type":"paragraph","position":{"start":{"line":1,"column":1},"end":{"line":1,"column":1}},"children":[{"type":"text","value":"Let’s examine the columns of our dataframe:","position":{"start":{"line":1,"column":1},"end":{"line":1,"column":1}},"key":"dcVORZD1PP"}],"key":"YG29eErHjO"}],"key":"EBH21UKdlt"},{"type":"block","kind":"notebook-code","children":[{"type":"code","lang":"python","executable":true,"value":"column_names = df.columns.tolist()\nprint(column_names)","key":"hUVSaVSocJ"},{"type":"outputs","id":"Ve_B8yFDBwZbHr2rYEMux","children":[{"type":"output","children":[],"jupyter_data":{"output_type":"stream","name":"stdout","text":"['TEMP_C_0_m', 'T_DEWPOINT_C_0_m', 'PRES_Pa_0_m', 'UGRD_m/s_0_m', 'VGRD_m/s_0_m', 'ptype']\n"},"key":"pVz11QM5Qu"}],"key":"RWr61FKTKT"}],"key":"P6Vl6TtXjs"},{"type":"block","kind":"notebook-content","children":[{"type":"paragraph","position":{"start":{"line":1,"column":1},"end":{"line":1,"column":1}},"children":[{"type":"text","value":"These names stand for Temperature and Dewpoint Temperature, (both in degrees Celsius), Atmospheric Pressure in Pascals, U and V components of the Wind in meters per second, and finally, Precipitation Type. All of these variables are measured at ground level.","position":{"start":{"line":1,"column":1},"end":{"line":1,"column":1}},"key":"osN2aorFDb"}],"key":"cyMtf81qnp"}],"key":"ZWjRrZMEqg"},{"type":"block","kind":"notebook-content","children":[{"type":"heading","depth":2,"position":{"start":{"line":1,"column":1},"end":{"line":1,"column":1}},"children":[{"type":"text","value":"Let’s do EDA","position":{"start":{"line":1,"column":1},"end":{"line":1,"column":1}},"key":"JDIsXHcb9f"}],"identifier":"lets-do-eda","label":"Let’s do EDA","html_id":"lets-do-eda","implicit":true,"key":"FtK5SiqACH"}],"key":"gbqMqDyCZ8"},{"type":"block","kind":"notebook-content","children":[{"type":"paragraph","position":{"start":{"line":1,"column":1},"end":{"line":1,"column":1}},"children":[{"type":"text","value":"After we have imported our data, the next step is to explore it. This part is called Exploratory Data Analysis (EDA). The ","position":{"start":{"line":1,"column":1},"end":{"line":1,"column":1}},"key":"OjsEcTC4iu"},{"type":"inlineCode","value":"describe()","position":{"start":{"line":1,"column":1},"end":{"line":1,"column":1}},"key":"WZ4m8OKusL"},{"type":"text","value":" function will give us some descriptive statistics about our columns with numeric values.","position":{"start":{"line":1,"column":1},"end":{"line":1,"column":1}},"key":"EflVIASvwZ"}],"key":"udU5kEqjPo"}],"key":"kcQ1pPOacg"},{"type":"block","kind":"notebook-code","children":[{"type":"code","lang":"python","executable":true,"value":"df.describe()","key":"PKqwUYlCtA"},{"type":"outputs","id":"lsQndV-_o90S2bN75fzQi","children":[{"type":"output","children":[],"jupyter_data":{"output_type":"execute_result","execution_count":6,"metadata":{},"data":{"text/plain":{"content":"        TEMP_C_0_m  T_DEWPOINT_C_0_m    PRES_Pa_0_m  UGRD_m/s_0_m  \\\ncount  2000.000000       2000.000000    2000.000000   2000.000000   \nmean      7.191655          4.295661   97771.921875      0.245982   \nstd      11.015686         10.693260    4340.965332      3.244669   \nmin     -19.339417        -23.740677   68586.640625    -12.982805   \n25%      -0.677414         -3.349205   97349.937500     -1.848213   \n50%       2.912354          0.713211   98749.937500     -0.040516   \n75%      17.254036         14.244499  100049.683594      2.224049   \nmax      33.993225         26.039459  103628.171875     11.791678   \n\n       VGRD_m/s_0_m  \ncount   2000.000000  \nmean      -0.635261  \nstd        3.497568  \nmin      -12.780014  \n25%       -2.909421  \n50%       -0.531640  \n75%        1.671326  \nmax       11.930449  ","content_type":"text/plain"},"text/html":{"content":"<div>\n<style scoped>\n    .dataframe tbody tr th:only-of-type {\n        vertical-align: middle;\n    }\n\n    .dataframe tbody tr th {\n        vertical-align: top;\n    }\n\n    .dataframe thead th {\n        text-align: right;\n    }\n</style>\n<table border=\"1\" class=\"dataframe\">\n  <thead>\n    <tr style=\"text-align: right;\">\n      <th></th>\n      <th>TEMP_C_0_m</th>\n      <th>T_DEWPOINT_C_0_m</th>\n      <th>PRES_Pa_0_m</th>\n      <th>UGRD_m/s_0_m</th>\n      <th>VGRD_m/s_0_m</th>\n    </tr>\n  </thead>\n  <tbody>\n    <tr>\n      <th>count</th>\n      <td>2000.000000</td>\n      <td>2000.000000</td>\n      <td>2000.000000</td>\n      <td>2000.000000</td>\n      <td>2000.000000</td>\n    </tr>\n    <tr>\n      <th>mean</th>\n      <td>7.191655</td>\n      <td>4.295661</td>\n      <td>97771.921875</td>\n      <td>0.245982</td>\n      <td>-0.635261</td>\n    </tr>\n    <tr>\n      <th>std</th>\n      <td>11.015686</td>\n      <td>10.693260</td>\n      <td>4340.965332</td>\n      <td>3.244669</td>\n      <td>3.497568</td>\n    </tr>\n    <tr>\n      <th>min</th>\n      <td>-19.339417</td>\n      <td>-23.740677</td>\n      <td>68586.640625</td>\n      <td>-12.982805</td>\n      <td>-12.780014</td>\n    </tr>\n    <tr>\n      <th>25%</th>\n      <td>-0.677414</td>\n      <td>-3.349205</td>\n      <td>97349.937500</td>\n      <td>-1.848213</td>\n      <td>-2.909421</td>\n    </tr>\n    <tr>\n      <th>50%</th>\n      <td>2.912354</td>\n      <td>0.713211</td>\n      <td>98749.937500</td>\n      <td>-0.040516</td>\n      <td>-0.531640</td>\n    </tr>\n    <tr>\n      <th>75%</th>\n      <td>17.254036</td>\n      <td>14.244499</td>\n      <td>100049.683594</td>\n      <td>2.224049</td>\n      <td>1.671326</td>\n    </tr>\n    <tr>\n      <th>max</th>\n      <td>33.993225</td>\n      <td>26.039459</td>\n      <td>103628.171875</td>\n      <td>11.791678</td>\n      <td>11.930449</td>\n    </tr>\n  </tbody>\n</table>\n</div>","content_type":"text/html"}}},"key":"NZgNmtahM0"}],"key":"Aamo0NUvZa"}],"key":"eJ8xqOGar4"},{"type":"block","kind":"notebook-content","children":[{"type":"paragraph","position":{"start":{"line":1,"column":1},"end":{"line":1,"column":1}},"children":[{"type":"text","value":"Take a look at the count row, we have 2000 entries in each column, so there is no missing data! Each variable has different means, but some have different standard deviations.","position":{"start":{"line":1,"column":1},"end":{"line":1,"column":1}},"key":"lPNNbk1bpc"}],"key":"NkEDukmEmq"},{"type":"paragraph","position":{"start":{"line":3,"column":1},"end":{"line":3,"column":1}},"children":[{"type":"text","value":"It is easier to see the relationship between our variables if we plot them:","position":{"start":{"line":3,"column":1},"end":{"line":3,"column":1}},"key":"gRSQpfZzda"}],"key":"q53DHUs3O1"}],"key":"gzqmo6hvfK"},{"type":"block","kind":"notebook-code","children":[{"type":"code","lang":"python","executable":true,"value":"sns.pairplot(df, hue='ptype')","key":"lbNmqWZm8g"},{"type":"outputs","id":"QmDdFdargMZxwYTZp_VKZ","children":[{"type":"output","children":[],"jupyter_data":{"output_type":"execute_result","execution_count":7,"metadata":{},"data":{"text/plain":{"content":"<seaborn.axisgrid.PairGrid at 0x7fdd7f988440>","content_type":"text/plain"}}},"key":"JKJGsF4UYs"},{"type":"output","children":[],"jupyter_data":{"output_type":"display_data","metadata":{},"data":{"text/plain":{"content":"<Figure size 1335.75x1250 with 30 Axes>","content_type":"text/plain"},"image/png":{"content_type":"image/png","hash":"b05be57305dddf24d7e20b9470ed2be3","path":"/ptype-ml-cookbook/build/b05be57305dddf24d7e20b9470ed2be3.png"}}},"key":"qLbkbZ05IB"}],"key":"Vtu8w38SCd"}],"key":"bBTqI0qPUc"},{"type":"block","kind":"notebook-content","children":[{"type":"paragraph","position":{"start":{"line":1,"column":1},"end":{"line":1,"column":1}},"children":[{"type":"text","value":"Notice any trends so far? What input features might be the most important?","position":{"start":{"line":1,"column":1},"end":{"line":1,"column":1}},"key":"Qn6x2GtuXH"}],"key":"nTluxk8t83"},{"type":"paragraph","position":{"start":{"line":3,"column":1},"end":{"line":3,"column":1}},"children":[{"type":"text","value":"Next we can plot the Correlation Matrix. As the name suggests, this will show us the correlation between variables. The closer the absolute value is to 1, the stronger the relationship between these variables is. Notice how all of our diagonal values equal to 1? this is because they represent the correlation between a variable and itself. Can you see which other variables have strong correlations?","position":{"start":{"line":3,"column":1},"end":{"line":3,"column":1}},"key":"bGU94v0OjI"}],"key":"ssKx1nANZq"},{"type":"paragraph","position":{"start":{"line":5,"column":1},"end":{"line":5,"column":1}},"children":[{"type":"text","value":"For further reading, visit ","position":{"start":{"line":5,"column":1},"end":{"line":5,"column":1}},"key":"Cb0EX6NvX4"},{"type":"link","url":"https://towardsdatascience.com/correlation-matrix-demystified-3ae3405c86c1","position":{"start":{"line":5,"column":1},"end":{"line":5,"column":1}},"children":[{"type":"text","value":"Correlation Matrix, Demystified","position":{"start":{"line":5,"column":1},"end":{"line":5,"column":1}},"key":"W7rYLWOj01"}],"urlSource":"https://towardsdatascience.com/correlation-matrix-demystified-3ae3405c86c1","key":"kKi2lcjj05"}],"key":"dA7xs2SlOD"}],"key":"oH2JguEqRm"},{"type":"block","kind":"notebook-code","children":[{"type":"code","lang":"python","executable":true,"value":"plt.figure(figsize=(10, 8))\nsns.heatmap(df.select_dtypes(include=['number']).corr(), vmin=-1, vmax=1, cmap='coolwarm', annot=True)\nplt.title('Correlation Matrix')\nplt.show()","key":"aHqFUib4Up"},{"type":"outputs","id":"V5RizeAyGQEaiHVTsEkX6","children":[{"type":"output","children":[],"jupyter_data":{"output_type":"display_data","metadata":{},"data":{"text/plain":{"content":"<Figure size 1000x800 with 2 Axes>","content_type":"text/plain"},"image/png":{"content_type":"image/png","hash":"33d5c526067f88a345760a012a71806b","path":"/ptype-ml-cookbook/build/33d5c526067f88a345760a012a71806b.png"}}},"key":"VLg2RmdveO"}],"key":"wWw4VPSyx7"}],"key":"xxi4eCT9qc"},{"type":"block","kind":"notebook-content","children":[{"type":"heading","depth":2,"position":{"start":{"line":1,"column":1},"end":{"line":1,"column":1}},"children":[{"type":"text","value":"Splitting Datasets","position":{"start":{"line":1,"column":1},"end":{"line":1,"column":1}},"key":"Wv8tp9UGcM"}],"identifier":"splitting-datasets","label":"Splitting Datasets","html_id":"splitting-datasets","implicit":true,"key":"ULB3V7ec8o"}],"key":"phFd1pfgNW"},{"type":"block","kind":"notebook-content","children":[{"type":"paragraph","position":{"start":{"line":1,"column":1},"end":{"line":2,"column":1}},"children":[{"type":"text","value":"In this section we will learn how to split our data into the training, validation, and testing sets. As the name suggests, training set is used to teach the model about the data, while validation and testing sets are used to asses the performance of the model.\nTo learn more about the differences between the three, read the following article: ","position":{"start":{"line":1,"column":1},"end":{"line":1,"column":1}},"key":"VPhfHHcnoi"},{"type":"link","url":"https://machinelearningmastery.com/difference-test-validation-datasets/","position":{"start":{"line":1,"column":1},"end":{"line":1,"column":1}},"children":[{"type":"text","value":"What is the Difference Between Test and Validation Datasets?","position":{"start":{"line":1,"column":1},"end":{"line":1,"column":1}},"key":"qqpWIpvCTt"}],"urlSource":"https://machinelearningmastery.com/difference-test-validation-datasets/","key":"HaP29BDPLz"},{"type":"text","value":" Or browse through this module to also learn more details about the ML framework: ","position":{"start":{"line":1,"column":1},"end":{"line":1,"column":1}},"key":"qeYxFmQqqL"},{"type":"link","url":"https://elearning.unidata.ucar.edu/dataeLearning/Cybertraining/foundations/","position":{"start":{"line":1,"column":1},"end":{"line":1,"column":1}},"children":[{"type":"text","value":"Machine Learning Foundations in the Earth Systems Sciences","position":{"start":{"line":1,"column":1},"end":{"line":1,"column":1}},"key":"kw9ZaD31kI"}],"urlSource":"https://elearning.unidata.ucar.edu/dataeLearning/Cybertraining/foundations/","key":"N4OV3T08T0"}],"key":"SDa8vvBFbr"}],"key":"oFZ9dbpq4R"},{"type":"block","kind":"notebook-code","children":[{"type":"code","lang":"python","executable":true,"value":"from sklearn.model_selection import train_test_split","key":"iNf7Hj4zDf"},{"type":"outputs","id":"eeza8tKyvEsEy8yCGjUDv","children":[],"key":"Q0FLGMaNVk"}],"key":"Kl7b0yOGmB"},{"type":"block","kind":"notebook-content","children":[{"type":"paragraph","position":{"start":{"line":1,"column":1},"end":{"line":1,"column":1}},"children":[{"type":"text","value":"For this notebook, we will be doing a regression problem. The ptype variable will just be used for EDA. This example uses Temperaturere, Pressure, and Wind Components (x variables) to determine the dewpoint (y variable).","position":{"start":{"line":1,"column":1},"end":{"line":1,"column":1}},"key":"OxiSCoodzH"}],"key":"jaqkhZiy54"}],"key":"N04qCEBsQH"},{"type":"block","kind":"notebook-code","children":[{"type":"code","lang":"python","executable":true,"value":"X = df[['TEMP_C_0_m', 'PRES_Pa_0_m','UGRD_m/s_0_m', 'VGRD_m/s_0_m' ]]\ny = df['T_DEWPOINT_C_0_m']","key":"UFl9CuuUAR"},{"type":"outputs","id":"N-wzKnPACOUJez_etHo0S","children":[],"key":"r8MF63bQXe"}],"key":"WA9N7GIwKY"},{"type":"block","kind":"notebook-code","children":[{"type":"code","lang":"python","executable":true,"value":"# Splitting into training and temporary set (70% training, 30% temporary)\nX_train, X_temp, y_train, y_temp = train_test_split(X, y, test_size=0.3, random_state=42)\n\n# Splitting the temporary set into testing and validation sets (20% testing, 10% validation of the original dataset)\nX_test, X_val, y_test, y_val = train_test_split(X_temp, y_temp, test_size=1/3, random_state=42)","key":"gZTphXfuPB"},{"type":"outputs","id":"jbz0NzELo2Byz7meIMDgC","children":[],"key":"wVImQRfZOj"}],"key":"LATuZZe1Cc"},{"type":"block","kind":"notebook-content","children":[{"type":"heading","depth":2,"position":{"start":{"line":1,"column":1},"end":{"line":1,"column":1}},"children":[{"type":"text","value":"Scaling Your Data","position":{"start":{"line":1,"column":1},"end":{"line":1,"column":1}},"key":"z4v3cJRHxK"}],"identifier":"scaling-your-data","label":"Scaling Your Data","html_id":"scaling-your-data","implicit":true,"key":"usjevcg9yn"}],"key":"Mc884PLuGD"},{"type":"block","kind":"notebook-content","children":[{"type":"paragraph","position":{"start":{"line":1,"column":1},"end":{"line":1,"column":1}},"children":[{"type":"text","value":"After we split the data, we must scale it. Scaling helps us make sure all features, or variables, contribute equally to the model. We will be using ","position":{"start":{"line":1,"column":1},"end":{"line":1,"column":1}},"key":"rN3q4M6bly"},{"type":"link","url":"https://scikit-learn.org/stable/modules/generated/sklearn.preprocessing.StandardScaler.html#sklearn.preprocessing.StandardScaler","position":{"start":{"line":1,"column":1},"end":{"line":1,"column":1}},"children":[{"type":"text","value":"scikit-learn’s ","position":{"start":{"line":1,"column":1},"end":{"line":1,"column":1}},"key":"aLM0eJd6pS"},{"type":"inlineCode","value":"StandardScaler()","position":{"start":{"line":1,"column":1},"end":{"line":1,"column":1}},"key":"e7nrNWHXH1"},{"type":"text","value":" function","position":{"start":{"line":1,"column":1},"end":{"line":1,"column":1}},"key":"atpn4VCgjE"}],"urlSource":"https://scikit-learn.org/stable/modules/generated/sklearn.preprocessing.StandardScaler.html#sklearn.preprocessing.StandardScaler","key":"SivJ2nk0NV"},{"type":"text","value":", which standardizes our features by substracting the mean from each observation and then dividing by the standard deviation.","position":{"start":{"line":1,"column":1},"end":{"line":1,"column":1}},"key":"xmlg0F3O8w"}],"key":"Ni3gOGS5Sc"}],"key":"HTLeAS4c9F"},{"type":"block","kind":"notebook-code","children":[{"type":"code","lang":"python","executable":true,"value":"from sklearn.preprocessing import StandardScaler","key":"kInF09U6kP"},{"type":"outputs","id":"6FOgYfPSNansIKvHt57wy","children":[],"key":"nw04bgt8Ea"}],"key":"mLoqZ54N5m"},{"type":"block","kind":"notebook-code","children":[{"type":"code","lang":"python","executable":true,"value":"# Initialize the scaler\nscaler = StandardScaler()","key":"oYjaBNAn38"},{"type":"outputs","id":"FfOLUbKcKADbXzpm4ffkD","children":[],"key":"Oxy8nV02P4"}],"key":"ZaoVCDus2l"},{"type":"block","kind":"notebook-content","children":[{"type":"paragraph","position":{"start":{"line":1,"column":1},"end":{"line":1,"column":1}},"children":[{"type":"text","value":"In the following code, the ","position":{"start":{"line":1,"column":1},"end":{"line":1,"column":1}},"key":"RnjXgfUZA3"},{"type":"inlineCode","value":"fit_transform()","position":{"start":{"line":1,"column":1},"end":{"line":1,"column":1}},"key":"AuyqljVCBO"},{"type":"text","value":" function calculates the mean and standard deviation (fit) of ","position":{"start":{"line":1,"column":1},"end":{"line":1,"column":1}},"key":"qNRluCCx3r"},{"type":"inlineCode","value":"X_train","position":{"start":{"line":1,"column":1},"end":{"line":1,"column":1}},"key":"ufwDDvUE8I"},{"type":"text","value":", and then uses those parameters to scale the data (transform).","position":{"start":{"line":1,"column":1},"end":{"line":1,"column":1}},"key":"AdNfnZauWP"}],"key":"JQECs3IvoA"}],"key":"NJ75fDxJMP"},{"type":"block","kind":"notebook-code","children":[{"type":"code","lang":"python","executable":true,"value":"# Fit the scaler to the training data and transform it\nX_train_scaled = scaler.fit_transform(X_train)\n\n# Transform the testing and validation data using the same scaler\nX_test_scaled = scaler.transform(X_test)\nX_val_scaled = scaler.transform(X_val)","key":"JsiWIMFryQ"},{"type":"outputs","id":"EtmzNo7tYTrXm3HW5a-II","children":[],"key":"shiGkp2J8X"}],"key":"YgNLTIpPBn"},{"type":"block","kind":"notebook-content","children":[{"type":"paragraph","position":{"start":{"line":1,"column":1},"end":{"line":1,"column":1}},"children":[{"type":"text","value":"Notice how we are using ","position":{"start":{"line":1,"column":1},"end":{"line":1,"column":1}},"key":"DqJxbVXnwU"},{"type":"inlineCode","value":"transform()","position":{"start":{"line":1,"column":1},"end":{"line":1,"column":1}},"key":"GCLVu1eG7D"},{"type":"text","value":" on our testing and validation data instead. This allows us to use the same mean and invariance as in the training set and keep the testing/validation data “unseen”. This last part is especially important to maintain an unbiased model.","position":{"start":{"line":1,"column":1},"end":{"line":1,"column":1}},"key":"rOGylq9qjL"}],"key":"n0I8wCJx2z"},{"type":"paragraph","position":{"start":{"line":3,"column":1},"end":{"line":3,"column":1}},"children":[{"type":"text","value":"The following article provides a more detailed explanation: ","position":{"start":{"line":3,"column":1},"end":{"line":3,"column":1}},"key":"zWMnJC2SHh"},{"type":"link","url":"https://towardsdatascience.com/what-and-why-behind-fit-transform-vs-transform-in-scikit-learn-78f915cf96fe","position":{"start":{"line":3,"column":1},"end":{"line":3,"column":1}},"children":[{"type":"text","value":"What and why behind fit_transform() and transform() in scikit-learn!","position":{"start":{"line":3,"column":1},"end":{"line":3,"column":1}},"key":"HG12P0GbP3"}],"urlSource":"https://towardsdatascience.com/what-and-why-behind-fit-transform-vs-transform-in-scikit-learn-78f915cf96fe","key":"lKhqS6m9SH"}],"key":"L14VsAwK3c"}],"key":"SVWKlUUAf6"},{"type":"block","kind":"notebook-content","children":[{"type":"div","class":"admonition alert alert-info","children":[{"type":"paragraph","children":[{"type":"text","value":"Note","key":"HscPlRXKTB"}],"key":"yaxkqs4Ox3"},{"type":"text","value":"Always scale datasets after splitting to prevent data leakage!","key":"x2Mw3PNKQG"}],"key":"PCllbPpRSH"}],"key":"UpR1iKUKRc"},{"type":"block","kind":"notebook-content","children":[{"type":"heading","depth":2,"position":{"start":{"line":1,"column":1},"end":{"line":1,"column":1}},"children":[{"type":"text","value":"Machine Learning","position":{"start":{"line":1,"column":1},"end":{"line":1,"column":1}},"key":"u3N3OwSGmK"}],"identifier":"machine-learning","label":"Machine Learning","html_id":"machine-learning","implicit":true,"key":"BQnXhqSTRy"}],"key":"IyWpYvaUP7"},{"type":"block","kind":"notebook-content","children":[{"type":"heading","depth":3,"position":{"start":{"line":1,"column":1},"end":{"line":1,"column":1}},"children":[{"type":"text","value":"Training","position":{"start":{"line":1,"column":1},"end":{"line":1,"column":1}},"key":"VlQn9Imn92"}],"identifier":"training","label":"Training","html_id":"training","implicit":true,"key":"Xq7ZwYCbv9"}],"key":"ETx47PecUn"},{"type":"block","kind":"notebook-content","children":[{"type":"paragraph","position":{"start":{"line":1,"column":1},"end":{"line":1,"column":1}},"children":[{"type":"text","value":"We will use a linear regression model:","position":{"start":{"line":1,"column":1},"end":{"line":1,"column":1}},"key":"xV1a4lzOiI"}],"key":"Qju9pKv2WE"}],"key":"kK7PnItcsR"},{"type":"block","kind":"notebook-code","children":[{"type":"code","lang":"python","executable":true,"value":"from sklearn.linear_model import LinearRegression","key":"U89RpNof7A"},{"type":"outputs","id":"1Tk8G6AiuY_1GJI1bBiBW","children":[],"key":"CHSLdlIjan"}],"key":"PVnw13oHFf"},{"type":"block","kind":"notebook-code","children":[{"type":"code","lang":"python","executable":true,"value":"# Initialize the Logistic Regression model\nmodel = LinearRegression()","key":"frp4NhL1wd"},{"type":"outputs","id":"XHBzCS4NU07tBeEsyvYTN","children":[],"key":"lbJ5XKhdcG"}],"key":"hfg3NRooEm"},{"type":"block","kind":"notebook-code","children":[{"type":"code","lang":"python","executable":true,"value":"# Train the model with the training data\nmodel.fit(X_train_scaled, y_train)","key":"vqrkk8iLYk"},{"type":"outputs","id":"mkoZPk1bOpdXqQlIccWdW","children":[{"type":"output","children":[],"jupyter_data":{"output_type":"execute_result","execution_count":17,"metadata":{},"data":{"text/plain":{"content":"LinearRegression()","content_type":"text/plain"},"text/html":{"content_type":"text/html","hash":"99e5563e6339c0e06e88e2f877aedd26","path":"/ptype-ml-cookbook/build/99e5563e6339c0e06e88e2f877aedd26.html"}}},"key":"LX7aZJiWll"}],"key":"hPxsnDNNrV"}],"key":"OvIEaUUrRR"},{"type":"block","kind":"notebook-content","children":[{"type":"paragraph","position":{"start":{"line":1,"column":1},"end":{"line":1,"column":1}},"children":[{"type":"text","value":"Next step, let’s use the testing data and plot the new predicted values vs true values.","position":{"start":{"line":1,"column":1},"end":{"line":1,"column":1}},"key":"GQA3bEICOK"}],"key":"Kba7cnhY4P"}],"key":"DXbDKHZKHw"},{"type":"block","kind":"notebook-code","children":[{"type":"code","lang":"python","executable":true,"value":"# Predicting the Test set results\ny_pred = model.predict(X_test_scaled)","key":"Mk7MgT7GvI"},{"type":"outputs","id":"DJZBHNPm6bIMywsO7I1S1","children":[],"key":"KMR4Nc356j"}],"key":"ZvpODvO7ih"},{"type":"block","kind":"notebook-code","children":[{"type":"code","lang":"python","executable":true,"value":"# Create scatter plot\nplt.scatter(y_test, y_pred, alpha=0.2)\n\n# Add axis labels\nplt.xlabel('True Values')\nplt.ylabel('Predicted Values')\n\n# Set the same limits for both axes\nmin_val = min(min(y_test), min(y_pred))\nmax_val = max(max(y_test), max(y_pred))\nplt.xlim(min_val, max_val)\nplt.ylim(min_val, max_val)\n\n# Add a diagonal line for reference\nplt.plot([min_val, max_val], [min_val, max_val], 'r--')\n\n# Show the plot\nplt.show()","key":"ai0xwQ362I"},{"type":"outputs","id":"G1aNwcQ-kxsJraqiOvjEH","children":[{"type":"output","children":[],"jupyter_data":{"output_type":"display_data","metadata":{},"data":{"text/plain":{"content":"<Figure size 640x480 with 1 Axes>","content_type":"text/plain"},"image/png":{"content_type":"image/png","hash":"aa4ba0d50da88eb8e0c7e5f0c3d3924f","path":"/ptype-ml-cookbook/build/aa4ba0d50da88eb8e0c7e5f0c3d3924f.png"}}},"key":"pE1WENt7Rk"}],"key":"SjE8kC8oba"}],"key":"cW5Hqr77I4"},{"type":"block","kind":"notebook-content","children":[{"type":"heading","depth":3,"position":{"start":{"line":1,"column":1},"end":{"line":1,"column":1}},"children":[{"type":"text","value":"Regression Metrics","position":{"start":{"line":1,"column":1},"end":{"line":1,"column":1}},"key":"Vt5WlNq5Oi"}],"identifier":"regression-metrics","label":"Regression Metrics","html_id":"regression-metrics","implicit":true,"key":"H2x60dwC82"}],"key":"L9yDnMek7q"},{"type":"block","kind":"notebook-code","children":[{"type":"code","lang":"python","executable":true,"value":"from sklearn.metrics import root_mean_squared_error, r2_score\n\n# Calculate RMSE & R2\nrmse = root_mean_squared_error(y_test, y_pred)\nr2 = r2_score(y_test, y_pred)\n\nprint(f\"RMSE on Test Set: {rmse:.2f}\")\nprint(f\"R-squared (R2) on Test Set: {r2:.2f}\")","key":"iiODH0cbk6"},{"type":"outputs","id":"ndQgxDyxA5RUGTszX5scd","children":[{"type":"output","children":[],"jupyter_data":{"output_type":"stream","name":"stdout","text":"RMSE on Test Set: 3.23\nR-squared (R2) on Test Set: 0.91\n"},"key":"LkLJ78niP8"}],"key":"cebWiT4SdP"}],"key":"nBMqyFx0eh"},{"type":"block","kind":"notebook-content","children":[{"type":"paragraph","position":{"start":{"line":1,"column":1},"end":{"line":1,"column":1}},"children":[{"type":"text","value":"R-squared (R²) and Root Mean Squared Error (RMSE) are both metrics used to evaluate the performance of regression models, but they convey different types of information.","position":{"start":{"line":1,"column":1},"end":{"line":1,"column":1}},"key":"cezSsZTlV0"}],"key":"lvPEsIXxnf"},{"type":"paragraph","position":{"start":{"line":3,"column":1},"end":{"line":3,"column":1}},"children":[{"type":"text","value":"R², also known as the coefficient of determination, measures the proportion of the variance in the dependent variable that is predictable from the independent variables. It ranges from 0 to 1, where a higher value indicates a better fit of the model to the data, with 1 representing a perfect fit.","position":{"start":{"line":3,"column":1},"end":{"line":3,"column":1}},"key":"snm1w0rHwC"}],"key":"zOBiMoZHKx"},{"type":"paragraph","position":{"start":{"line":5,"column":1},"end":{"line":5,"column":1}},"children":[{"type":"text","value":"RMSE, on the other hand, quantifies the average magnitude of the prediction errors, providing an absolute measure of fit in the same units as the dependent variable. It calculates the square root of the average squared differences between predicted and observed values, with a lower RMSE indicating a model that predicts more accurately. While R² gives a sense of how well the model explains the variability of the data, RMSE provides a direct measure of the model’s prediction accuracy.","position":{"start":{"line":5,"column":1},"end":{"line":5,"column":1}},"key":"tQltz29Lsd"}],"key":"ykweSmx94h"},{"type":"paragraph","position":{"start":{"line":7,"column":1},"end":{"line":7,"column":1}},"children":[{"type":"text","value":"This ","position":{"start":{"line":7,"column":1},"end":{"line":7,"column":1}},"key":"lhQqFkX4C1"},{"type":"link","url":"https://www.unidata.ucar.edu/blogs/news/entry/r-sup-2-sup-downsides","position":{"start":{"line":7,"column":1},"end":{"line":7,"column":1}},"children":[{"type":"text","value":"blog post","position":{"start":{"line":7,"column":1},"end":{"line":7,"column":1}},"key":"yFijGgnUiZ"}],"urlSource":"https://www.unidata.ucar.edu/blogs/news/entry/r-sup-2-sup-downsides","key":"u7KE1kOxoz"},{"type":"text","value":" covers some of the downsides to looking at R2 alone.","position":{"start":{"line":7,"column":1},"end":{"line":7,"column":1}},"key":"CwpeZsJsNa"}],"key":"b7OXBZpuMn"}],"key":"MyQB6FQBeR"},{"type":"block","kind":"notebook-content","children":[{"type":"heading","depth":3,"position":{"start":{"line":1,"column":1},"end":{"line":1,"column":1}},"children":[{"type":"text","value":"Now let’s try it on the validation set","position":{"start":{"line":1,"column":1},"end":{"line":1,"column":1}},"key":"JWzK9zKmZQ"}],"identifier":"now-lets-try-it-on-the-validation-set","label":"Now let’s try it on the validation set","html_id":"now-lets-try-it-on-the-validation-set","implicit":true,"key":"mtkYC1rzJ9"}],"key":"BLyEHfpM3T"},{"type":"block","kind":"notebook-content","children":[{"type":"paragraph","position":{"start":{"line":1,"column":1},"end":{"line":1,"column":1}},"children":[{"type":"text","value":"At this point we could make some changes to our model based on the metrics we got after testing and repeat the training and testing process. Once we are done we can proceed to validate model:","position":{"start":{"line":1,"column":1},"end":{"line":1,"column":1}},"key":"nJ5cpbGJl3"}],"key":"oMAQ3bWgxu"}],"key":"yvsUiwI4OA"},{"type":"block","kind":"notebook-code","children":[{"type":"code","lang":"python","executable":true,"value":"# Predicting the Validation set results\ny_val_pred = model.predict(X_val_scaled)\n\n# Calculate RMSE & R2\nrmse_val = root_mean_squared_error(y_val, y_val_pred)\nr2_val = r2_score(y_val, y_val_pred)\n\nprint(f\"RMSE on Validation Set: {rmse_val:.2f}\")\nprint(f\"R-squared (R2) on Validation Set: {r2_val:.2f}\")","key":"hLOtVyaQfO"},{"type":"outputs","id":"Q0dFH8jscvXRRDjPBOTvt","children":[{"type":"output","children":[],"jupyter_data":{"output_type":"stream","name":"stdout","text":"RMSE on Validation Set: 2.36\nR-squared (R2) on Validation Set: 0.95\n"},"key":"YmeiREwtcl"}],"key":"ItDOwhWuTV"}],"key":"CtJugLle8a"},{"type":"block","kind":"notebook-content","children":[{"type":"heading","depth":2,"position":{"start":{"line":1,"column":1},"end":{"line":1,"column":1}},"children":[{"type":"text","value":"Different dataset, different results?","position":{"start":{"line":1,"column":1},"end":{"line":1,"column":1}},"key":"N3J4zoyB0E"}],"identifier":"different-dataset-different-results","label":"Different dataset, different results?","html_id":"different-dataset-different-results","implicit":true,"key":"u7QJfvfgT3"}],"key":"kbC0uRh4hy"},{"type":"block","kind":"notebook-content","children":[{"type":"paragraph","position":{"start":{"line":1,"column":1},"end":{"line":1,"column":1}},"children":[{"type":"text","value":"Let’s look at another dataset. This dataset just has snow and freezing rain as the p-types, so overall it will be colder. Let’s see if we get similar results.","position":{"start":{"line":1,"column":1},"end":{"line":1,"column":1}},"key":"MCdeiX99sI"}],"key":"LhWTodCABu"}],"key":"gFsX9MXaLM"},{"type":"block","kind":"notebook-code","children":[{"type":"code","lang":"python","executable":true,"value":"df_frza = pd.read_parquet(r'../0_data/ptype_sampled_frza.parquet')","key":"tDFlLUCFcl"},{"type":"outputs","id":"gbCaHYKx0yLgh-PjbM3wY","children":[],"key":"CTGbMM29Q7"}],"key":"sSL32boAkQ"},{"type":"block","kind":"notebook-code","children":[{"type":"code","lang":"python","executable":true,"value":"df_frza.describe()","key":"A8sTVApF5g"},{"type":"outputs","id":"nvWWnjEfIP74Z-bTji7aq","children":[{"type":"output","children":[],"jupyter_data":{"output_type":"execute_result","execution_count":23,"metadata":{},"data":{"text/plain":{"content":"        TEMP_C_0_m  T_DEWPOINT_C_0_m    PRES_Pa_0_m  UGRD_m/s_0_m  \\\ncount  2000.000000       2000.000000    2000.000000   2000.000000   \nmean     -1.224230         -3.480852   97853.976562     -0.276727   \nstd       4.247178          4.457617    4084.322754      3.331566   \nmin     -19.303024        -24.025223   67854.320312    -11.178705   \n25%      -3.115570         -5.516388   97356.414062     -2.465180   \n50%      -0.692780         -2.609085   98588.738281     -0.602569   \n75%       0.643044         -0.705284   99923.923828      1.779485   \nmax      27.657043         25.156921  103556.835938     16.121258   \n\n       VGRD_m/s_0_m  \ncount   2000.000000  \nmean      -1.568403  \nstd        3.333238  \nmin      -14.452679  \n25%       -3.786891  \n50%       -1.692378  \n75%        0.665858  \nmax       10.243851  ","content_type":"text/plain"},"text/html":{"content":"<div>\n<style scoped>\n    .dataframe tbody tr th:only-of-type {\n        vertical-align: middle;\n    }\n\n    .dataframe tbody tr th {\n        vertical-align: top;\n    }\n\n    .dataframe thead th {\n        text-align: right;\n    }\n</style>\n<table border=\"1\" class=\"dataframe\">\n  <thead>\n    <tr style=\"text-align: right;\">\n      <th></th>\n      <th>TEMP_C_0_m</th>\n      <th>T_DEWPOINT_C_0_m</th>\n      <th>PRES_Pa_0_m</th>\n      <th>UGRD_m/s_0_m</th>\n      <th>VGRD_m/s_0_m</th>\n    </tr>\n  </thead>\n  <tbody>\n    <tr>\n      <th>count</th>\n      <td>2000.000000</td>\n      <td>2000.000000</td>\n      <td>2000.000000</td>\n      <td>2000.000000</td>\n      <td>2000.000000</td>\n    </tr>\n    <tr>\n      <th>mean</th>\n      <td>-1.224230</td>\n      <td>-3.480852</td>\n      <td>97853.976562</td>\n      <td>-0.276727</td>\n      <td>-1.568403</td>\n    </tr>\n    <tr>\n      <th>std</th>\n      <td>4.247178</td>\n      <td>4.457617</td>\n      <td>4084.322754</td>\n      <td>3.331566</td>\n      <td>3.333238</td>\n    </tr>\n    <tr>\n      <th>min</th>\n      <td>-19.303024</td>\n      <td>-24.025223</td>\n      <td>67854.320312</td>\n      <td>-11.178705</td>\n      <td>-14.452679</td>\n    </tr>\n    <tr>\n      <th>25%</th>\n      <td>-3.115570</td>\n      <td>-5.516388</td>\n      <td>97356.414062</td>\n      <td>-2.465180</td>\n      <td>-3.786891</td>\n    </tr>\n    <tr>\n      <th>50%</th>\n      <td>-0.692780</td>\n      <td>-2.609085</td>\n      <td>98588.738281</td>\n      <td>-0.602569</td>\n      <td>-1.692378</td>\n    </tr>\n    <tr>\n      <th>75%</th>\n      <td>0.643044</td>\n      <td>-0.705284</td>\n      <td>99923.923828</td>\n      <td>1.779485</td>\n      <td>0.665858</td>\n    </tr>\n    <tr>\n      <th>max</th>\n      <td>27.657043</td>\n      <td>25.156921</td>\n      <td>103556.835938</td>\n      <td>16.121258</td>\n      <td>10.243851</td>\n    </tr>\n  </tbody>\n</table>\n</div>","content_type":"text/html"}}},"key":"cVArluyK0m"}],"key":"adXlHDCU1b"}],"key":"bBMyWHnriF"},{"type":"block","kind":"notebook-code","children":[{"type":"code","lang":"python","executable":true,"value":"sns.pairplot(df_frza, hue='ptype')","key":"ufXcWMKE7G"},{"type":"outputs","id":"Pmbiv7c9DKVlVbdBhPxE-","children":[{"type":"output","children":[],"jupyter_data":{"output_type":"execute_result","execution_count":24,"metadata":{},"data":{"text/plain":{"content":"<seaborn.axisgrid.PairGrid at 0x7fdd342e1590>","content_type":"text/plain"}}},"key":"lDpOGLONy0"},{"type":"output","children":[],"jupyter_data":{"output_type":"display_data","metadata":{},"data":{"text/plain":{"content":"<Figure size 1335.75x1250 with 30 Axes>","content_type":"text/plain"},"image/png":{"content_type":"image/png","hash":"8abd6f5286e70cdf70945a974b7a08c5","path":"/ptype-ml-cookbook/build/8abd6f5286e70cdf70945a974b7a08c5.png"}}},"key":"JtSZyKlCJf"}],"key":"yuxGyfr5gx"}],"key":"pl7SHtJ52c"},{"type":"block","kind":"notebook-code","children":[{"type":"code","lang":"python","executable":true,"value":"plt.figure(figsize=(10, 8))\nsns.heatmap(df_frza.select_dtypes(include=['number']).corr(), vmin=-1, vmax=1, cmap='coolwarm', annot=True)\nplt.title('Correlation Matrix')\nplt.show()","key":"FPGQHuGFJk"},{"type":"outputs","id":"Mpmu-eP9vZa9iRzCyNaWM","children":[{"type":"output","children":[],"jupyter_data":{"output_type":"display_data","metadata":{},"data":{"text/plain":{"content":"<Figure size 1000x800 with 2 Axes>","content_type":"text/plain"},"image/png":{"content_type":"image/png","hash":"87293619bdbcf0df139c107746a2bc50","path":"/ptype-ml-cookbook/build/87293619bdbcf0df139c107746a2bc50.png"}}},"key":"yuzke2A63O"}],"key":"O2LWodOAUB"}],"key":"K3q83X64ZA"},{"type":"block","kind":"notebook-content","children":[{"type":"paragraph","position":{"start":{"line":1,"column":1},"end":{"line":1,"column":1}},"children":[{"type":"text","value":"What are the differences in EDA compared to rain vs snow? Do you expect this to do better or worse compared to rain vs snow?","position":{"start":{"line":1,"column":1},"end":{"line":1,"column":1}},"key":"oysztHNOd7"}],"key":"rUOOo5qJVb"}],"key":"hfsTrYEzP1"},{"type":"block","kind":"notebook-content","children":[{"type":"heading","depth":3,"position":{"start":{"line":1,"column":1},"end":{"line":1,"column":1}},"children":[{"type":"text","value":"Split up the data & Scale","position":{"start":{"line":1,"column":1},"end":{"line":1,"column":1}},"key":"Bh4ZPUZwqP"}],"identifier":"split-up-the-data-scale","label":"Split up the data & Scale","html_id":"split-up-the-data-scale","implicit":true,"key":"YWR2V0IegA"}],"key":"PY0ZDN8tkd"},{"type":"block","kind":"notebook-content","children":[{"type":"paragraph","position":{"start":{"line":1,"column":1},"end":{"line":1,"column":1}},"children":[{"type":"text","value":"The following code is a bit compressed, but is the same line for line as above, just with a new dataset.","position":{"start":{"line":1,"column":1},"end":{"line":1,"column":1}},"key":"xEuTwboLIe"}],"key":"BLHmE2mwSb"}],"key":"YkvJhKhWPJ"},{"type":"block","kind":"notebook-code","children":[{"type":"code","lang":"python","executable":true,"value":"X2 = df_frza[['TEMP_C_0_m',  'PRES_Pa_0_m','UGRD_m/s_0_m', 'VGRD_m/s_0_m' ]]\ny2 = df_frza['T_DEWPOINT_C_0_m']","key":"G3bJqZ9Kai"},{"type":"outputs","id":"XKbXC6l_AKpObyTlLGwey","children":[],"key":"vwRq419XM7"}],"key":"lrz4g790uf"},{"type":"block","kind":"notebook-code","children":[{"type":"code","lang":"python","executable":true,"value":"# Splitting into training and temporary set (70% training, 30% temporary)\nX_train2, X_temp2, y_train2, y_temp2 = train_test_split(X2, y2, test_size=0.3, random_state=42)\n\n# Splitting the temporary set into testing and validation sets (20% testing, 10% validation of the original dataset)\nX_test2, X_val2, y_test2, y_val2 = train_test_split(X_temp2, y_temp2, test_size=1/3, random_state=42)","key":"KDpUe79d9n"},{"type":"outputs","id":"0HLUEE-pvKfsqhGM6Glxd","children":[],"key":"pdAJHSVMOz"}],"key":"SUhyPvWxV2"},{"type":"block","kind":"notebook-code","children":[{"type":"code","lang":"python","executable":true,"value":"# Initialize the scaler\nscaler = StandardScaler()","key":"BIz52xG5zu"},{"type":"outputs","id":"8JV4cvh_7jf57Vu19Cadp","children":[],"key":"o0HYDMREAO"}],"key":"Wo2pMAtZ8i"},{"type":"block","kind":"notebook-code","children":[{"type":"code","lang":"python","executable":true,"value":"# Fit the scaler to the training data and transform it\nX_train_scaled2 = scaler.fit_transform(X_train2)\n\n# Transform the testing and validation data using the same scaler\nX_test_scaled2 = scaler.transform(X_test2)\nX_val_scaled2 = scaler.transform(X_val2)","key":"wh6MChHzVY"},{"type":"outputs","id":"G5Qb_o_aJtYW2QvWYfOyg","children":[],"key":"CQ2uEGSIsh"}],"key":"Jeo9wpDExH"},{"type":"block","kind":"notebook-content","children":[{"type":"paragraph","position":{"start":{"line":1,"column":1},"end":{"line":1,"column":1}},"children":[{"type":"text","value":"Notice the new model! We will be using a ","position":{"start":{"line":1,"column":1},"end":{"line":1,"column":1}},"key":"BTI7ItaE9P"},{"type":"link","url":"https://scikit-learn.org/stable/modules/tree.html","position":{"start":{"line":1,"column":1},"end":{"line":1,"column":1}},"children":[{"type":"text","value":"Decision Tree","position":{"start":{"line":1,"column":1},"end":{"line":1,"column":1}},"key":"c7Ecdux0L0"}],"urlSource":"https://scikit-learn.org/stable/modules/tree.html","key":"PnlcGhocN7"},{"type":"text","value":". If you want to learn more, here is a StatQuest ","position":{"start":{"line":1,"column":1},"end":{"line":1,"column":1}},"key":"OA2XNWvb1X"},{"type":"link","url":"https://www.youtube.com/watch?v=_L39rN6gz7Y","position":{"start":{"line":1,"column":1},"end":{"line":1,"column":1}},"children":[{"type":"text","value":"video","position":{"start":{"line":1,"column":1},"end":{"line":1,"column":1}},"key":"ap3IJ9WBdI"}],"urlSource":"https://www.youtube.com/watch?v=_L39rN6gz7Y","key":"OY93hC5cLE"},{"type":"text","value":".","position":{"start":{"line":1,"column":1},"end":{"line":1,"column":1}},"key":"JhU7Sn0uVa"}],"key":"ykvcFWhEyy"}],"key":"kMs310HuDx"},{"type":"block","kind":"notebook-code","children":[{"type":"code","lang":"python","executable":true,"value":"# Decision Tree Regressor\nfrom sklearn.tree import DecisionTreeRegressor\n\nmodel = DecisionTreeRegressor()","key":"RwIWREKasu"},{"type":"outputs","id":"tfiyIDZ1GfUW4TwBJBHp1","children":[],"key":"cJMmNS6Dzm"}],"key":"T1R6cwAH45"},{"type":"block","kind":"notebook-code","children":[{"type":"code","lang":"python","executable":true,"value":"# Train the model with the training data\nmodel.fit(X_train_scaled2, y_train2)","key":"yeQieCACNu"},{"type":"outputs","id":"dOnGa8k3oAhnnPV3BThuT","children":[{"type":"output","children":[],"jupyter_data":{"output_type":"execute_result","execution_count":31,"metadata":{},"data":{"text/plain":{"content":"DecisionTreeRegressor()","content_type":"text/plain"},"text/html":{"content_type":"text/html","hash":"ff7aab100f1a8013323c64d6c9ffda2e","path":"/ptype-ml-cookbook/build/ff7aab100f1a8013323c64d6c9ffda2e.html"}}},"key":"z2Cozl2lmX"}],"key":"yiHAL767UP"}],"key":"BgQVVq3bWH"},{"type":"block","kind":"notebook-content","children":[{"type":"heading","depth":3,"position":{"start":{"line":1,"column":1},"end":{"line":1,"column":1}},"children":[{"type":"text","value":"Test Set ML","position":{"start":{"line":1,"column":1},"end":{"line":1,"column":1}},"key":"YwBfb84wK2"}],"identifier":"test-set-ml","label":"Test Set ML","html_id":"test-set-ml","implicit":true,"key":"qn0KAufr7F"}],"key":"SLIs0aIgqu"},{"type":"block","kind":"notebook-code","children":[{"type":"code","lang":"python","executable":true,"value":"# Predicting the Test set results\ny_pred2 = model.predict(X_test_scaled2)","key":"H2evIb6wS1"},{"type":"outputs","id":"DZV9SVsGjduJ7Bufl54Yf","children":[],"key":"KcBk47pi8D"}],"key":"xW2s4vOJn6"},{"type":"block","kind":"notebook-code","children":[{"type":"code","lang":"python","executable":true,"value":"rmse = root_mean_squared_error(y_test2, y_pred2)\nr2 = r2_score(y_test2, y_pred2)\n\nprint(f\"RMSE on Test Set: {rmse:.2f}\")\nprint(f\"R-squared (R2) on Test Set: {r2:.2f}\")","key":"XuHIUGgvY4"},{"type":"outputs","id":"NoQyT5-GIOvwRhegOySRw","children":[{"type":"output","children":[],"jupyter_data":{"output_type":"stream","name":"stdout","text":"RMSE on Test Set: 2.84\nR-squared (R2) on Test Set: 0.57\n"},"key":"MI2gJSbMqG"}],"key":"dbAarya7PA"}],"key":"IdqWlRMSEN"},{"type":"block","kind":"notebook-code","children":[{"type":"code","lang":"python","executable":true,"value":"# Create scatter plot\nplt.scatter(y_test2, y_pred2, alpha=0.2)\n\n# Add axis labels\nplt.xlabel('True Values')\nplt.ylabel('Predicted Values')\n\n# Set the same limits for both axes\nmin_val = min(min(y_test2), min(y_pred2))\nmax_val = max(max(y_test2), max(y_pred2))\nplt.xlim(min_val, max_val)\nplt.ylim(min_val, max_val)\n\n# Add a diagonal line for reference\nplt.plot([min_val, max_val], [min_val, max_val], 'r--')\n\n# Show the plot\nplt.show()","key":"Dih1XyrQWl"},{"type":"outputs","id":"1OQ4MHDf4w8fWgLptAv77","children":[{"type":"output","children":[],"jupyter_data":{"output_type":"display_data","metadata":{},"data":{"text/plain":{"content":"<Figure size 640x480 with 1 Axes>","content_type":"text/plain"},"image/png":{"content_type":"image/png","hash":"7aeb681e1a458e4e6e493bf0462ffccc","path":"/ptype-ml-cookbook/build/7aeb681e1a458e4e6e493bf0462ffccc.png"}}},"key":"pfglranzlT"}],"key":"KKBNJE2AuG"}],"key":"Od2P6vpWdL"},{"type":"block","kind":"notebook-content","children":[{"type":"paragraph","position":{"start":{"line":1,"column":1},"end":{"line":1,"column":1}},"children":[{"type":"text","value":"What do you notice in this scatter plot compared to the one with rain vs snow?","position":{"start":{"line":1,"column":1},"end":{"line":1,"column":1}},"key":"nqV50RNEIK"}],"key":"qFi1GHtZD6"}],"key":"jHVilBR7lp"},{"type":"block","kind":"notebook-content","children":[{"type":"heading","depth":3,"position":{"start":{"line":1,"column":1},"end":{"line":1,"column":1}},"children":[{"type":"text","value":"Validation Set ML","position":{"start":{"line":1,"column":1},"end":{"line":1,"column":1}},"key":"DySLLkx9xE"}],"identifier":"validation-set-ml","label":"Validation Set ML","html_id":"validation-set-ml","implicit":true,"key":"LMPw16YL3G"}],"key":"el2eXtjmJJ"},{"type":"block","kind":"notebook-code","children":[{"type":"code","lang":"python","executable":true,"value":"# Predicting the Validation set results\ny_val_pred2 = model.predict(X_val_scaled2)\n\n# Calculate RMSE & R2\nrmse_val = root_mean_squared_error(y_val2, y_val_pred2)\nr2_val = r2_score(y_val2, y_val_pred2)\n\nprint(f\"RMSE on Validation Set: {rmse_val:.2f}\")\nprint(f\"R-squared (R2) on Validation Set: {r2_val:.2f}\")","key":"kPXjXpXHEZ"},{"type":"outputs","id":"iZaLN0U-0ekEsdfQtEVYm","children":[{"type":"output","children":[],"jupyter_data":{"output_type":"stream","name":"stdout","text":"RMSE on Validation Set: 2.59\nR-squared (R2) on Validation Set: 0.69\n"},"key":"oCcEezHNUC"}],"key":"y2xggTBEda"}],"key":"gtn6AulKba"},{"type":"block","kind":"notebook-content","children":[{"type":"heading","depth":3,"position":{"start":{"line":1,"column":1},"end":{"line":1,"column":1}},"children":[{"type":"text","value":"More Questions","position":{"start":{"line":1,"column":1},"end":{"line":1,"column":1}},"key":"opiSzpTGNV"}],"identifier":"more-questions","label":"More Questions","html_id":"more-questions","implicit":true,"key":"O02KEkMk5J"}],"key":"A2W2udJ2nu"},{"type":"block","kind":"notebook-content","children":[{"type":"list","ordered":true,"start":1,"spread":false,"position":{"start":{"line":1,"column":1},"end":{"line":5,"column":1}},"children":[{"type":"listItem","spread":true,"position":{"start":{"line":1,"column":1},"end":{"line":2,"column":1}},"children":[{"type":"paragraph","position":{"start":{"line":1,"column":1},"end":{"line":1,"column":1}},"children":[{"type":"text","value":"What do you see comparing the metrics; freezing rain vs snow and snow vs rain? Is this what you expected?","position":{"start":{"line":1,"column":1},"end":{"line":1,"column":1}},"key":"EkedbihJnS"}],"key":"v3aMW0dIXm"}],"key":"CFU9bdLtwx"},{"type":"listItem","spread":true,"position":{"start":{"line":3,"column":1},"end":{"line":4,"column":1}},"children":[{"type":"paragraph","position":{"start":{"line":3,"column":1},"end":{"line":3,"column":1}},"children":[{"type":"text","value":"Is the Decision Tree model consistent between testing and validations sets for both experiments? Could we potentially use a more complex model?","position":{"start":{"line":3,"column":1},"end":{"line":3,"column":1}},"key":"E0IBZlHqQf"}],"key":"aE4bWSz9Sr"}],"key":"pnRkscHuvN"},{"type":"listItem","spread":true,"position":{"start":{"line":5,"column":1},"end":{"line":5,"column":1}},"children":[{"type":"paragraph","position":{"start":{"line":5,"column":1},"end":{"line":5,"column":1}},"children":[{"type":"text","value":"How many lines of code does it take to do a quick ML analysis with a testing, training, and validation dataset?","position":{"start":{"line":5,"column":1},"end":{"line":5,"column":1}},"key":"iSF75Bd6Co"}],"key":"XYeDuRuIzk"}],"key":"iudKf5mbQf"}],"key":"gednHxPg14"}],"key":"rgPW8q0Dm4"},{"type":"block","kind":"notebook-content","children":[{"type":"thematicBreak","position":{"start":{"line":1,"column":1},"end":{"line":1,"column":1}},"key":"LMTe8FwCvO"}],"key":"sJyZOb7siK"},{"type":"block","kind":"notebook-content","children":[{"type":"heading","depth":2,"position":{"start":{"line":1,"column":1},"end":{"line":1,"column":1}},"children":[{"type":"text","value":"Summary","position":{"start":{"line":1,"column":1},"end":{"line":1,"column":1}},"key":"GLvExlw9rC"}],"identifier":"summary","label":"Summary","html_id":"summary","implicit":true,"key":"DrGo8c89rU"},{"type":"paragraph","position":{"start":{"line":2,"column":1},"end":{"line":2,"column":1}},"children":[{"type":"text","value":"In this notebook we learned:","position":{"start":{"line":2,"column":1},"end":{"line":2,"column":1}},"key":"H5Z9LD5a0X"}],"key":"C4Q4lGOcwX"},{"type":"list","ordered":true,"start":1,"spread":false,"position":{"start":{"line":3,"column":1},"end":{"line":6,"column":1}},"children":[{"type":"listItem","spread":true,"position":{"start":{"line":3,"column":1},"end":{"line":3,"column":1}},"children":[{"type":"paragraph","children":[{"type":"text","value":"What Exploratory Data Analysis is and some useful functions that can help you in the process of understading your data.","position":{"start":{"line":3,"column":1},"end":{"line":3,"column":1}},"key":"W9Yw6VPdEX"}],"key":"wKGtcJVtEA"}],"key":"YOMd4aTfLF"},{"type":"listItem","spread":true,"position":{"start":{"line":4,"column":1},"end":{"line":4,"column":1}},"children":[{"type":"paragraph","children":[{"type":"text","value":"How and why we split and scale data","position":{"start":{"line":4,"column":1},"end":{"line":4,"column":1}},"key":"Z0j1fQh0Yz"}],"key":"mIoFnPXWBm"}],"key":"c74sf1XChd"},{"type":"listItem","spread":true,"position":{"start":{"line":5,"column":1},"end":{"line":6,"column":1}},"children":[{"type":"paragraph","children":[{"type":"text","value":"How to train your model and evaluate its accuracy afterwards","position":{"start":{"line":5,"column":1},"end":{"line":5,"column":1}},"key":"LcTVklHYRA"}],"key":"B35kVLx6sD"}],"key":"GsZbyYrJd5"}],"key":"Q3TobQ7udT"},{"type":"heading","depth":3,"position":{"start":{"line":7,"column":1},"end":{"line":7,"column":1}},"children":[{"type":"text","value":"What’s next?","position":{"start":{"line":7,"column":1},"end":{"line":7,"column":1}},"key":"U2GPwe7gfi"}],"identifier":"whats-next","label":"What’s next?","html_id":"whats-next","implicit":true,"key":"rFYlAGC3i2"},{"type":"paragraph","position":{"start":{"line":8,"column":1},"end":{"line":8,"column":1}},"children":[{"type":"text","value":"Let Jupyter book tie this to the next (sequential) piece of content that people could move on to down below and in the sidebar. However, if this page uniquely enables your reader to tackle other nonsequential concepts throughout this book, or even external content, link to it here!","position":{"start":{"line":8,"column":1},"end":{"line":8,"column":1}},"key":"OAgOIYbNql"}],"key":"rHL4qTik5m"}],"key":"OBvHRCvDxg"},{"type":"block","kind":"notebook-content","children":[{"type":"heading","depth":2,"position":{"start":{"line":1,"column":1},"end":{"line":1,"column":1}},"children":[{"type":"text","value":"Resources and references","position":{"start":{"line":1,"column":1},"end":{"line":1,"column":1}},"key":"cuPW4gs5RP"}],"identifier":"resources-and-references","label":"Resources and references","html_id":"resources-and-references","implicit":true,"key":"UsZirqm3Nc"},{"type":"list","ordered":true,"start":1,"spread":false,"position":{"start":{"line":2,"column":1},"end":{"line":11,"column":1}},"children":[{"type":"listItem","spread":true,"position":{"start":{"line":2,"column":1},"end":{"line":2,"column":1}},"children":[{"type":"paragraph","children":[{"type":"link","url":"https://scikit-learn.org/stable/","position":{"start":{"line":2,"column":1},"end":{"line":2,"column":1}},"children":[{"type":"text","value":"Scikit-learn","position":{"start":{"line":2,"column":1},"end":{"line":2,"column":1}},"key":"XLXyUCDSdx"}],"urlSource":"https://scikit-learn.org/stable/","key":"HweZCbaYYR"}],"key":"DOyPn5cj4D"}],"key":"rbgfT78eWG"},{"type":"listItem","spread":true,"position":{"start":{"line":3,"column":1},"end":{"line":3,"column":1}},"children":[{"type":"paragraph","children":[{"type":"link","url":"https://towardsdatascience.com/correlation-matrix-demystified-3ae3405c86c1","position":{"start":{"line":3,"column":1},"end":{"line":3,"column":1}},"children":[{"type":"text","value":"Correlation Matrix, Demystified","position":{"start":{"line":3,"column":1},"end":{"line":3,"column":1}},"key":"vv3IZQf9zV"}],"urlSource":"https://towardsdatascience.com/correlation-matrix-demystified-3ae3405c86c1","key":"B3W4ELAxKc"}],"key":"sjj7kl3Fto"}],"key":"Qq4as81gE3"},{"type":"listItem","spread":true,"position":{"start":{"line":4,"column":1},"end":{"line":4,"column":1}},"children":[{"type":"paragraph","children":[{"type":"link","url":"https://machinelearningmastery.com/difference-test-validation-datasets/","position":{"start":{"line":4,"column":1},"end":{"line":4,"column":1}},"children":[{"type":"text","value":"What is the Difference Between Test and Validation Datasets?","position":{"start":{"line":4,"column":1},"end":{"line":4,"column":1}},"key":"MbgTdc84Bi"}],"urlSource":"https://machinelearningmastery.com/difference-test-validation-datasets/","key":"f0Sq2vwiwi"}],"key":"THc5ArDKoi"}],"key":"Clq7XzvBKC"},{"type":"listItem","spread":true,"position":{"start":{"line":5,"column":1},"end":{"line":5,"column":1}},"children":[{"type":"paragraph","children":[{"type":"link","url":"https://elearning.unidata.ucar.edu/dataeLearning/Cybertraining/foundations/","position":{"start":{"line":5,"column":1},"end":{"line":5,"column":1}},"children":[{"type":"text","value":"Machine Learning Foundations in the Earth Systems Sciences","position":{"start":{"line":5,"column":1},"end":{"line":5,"column":1}},"key":"y56YuRcKuY"}],"urlSource":"https://elearning.unidata.ucar.edu/dataeLearning/Cybertraining/foundations/","key":"Cd1W5XVXoX"}],"key":"UHKogQUJq1"}],"key":"lFTlnMO1Oi"},{"type":"listItem","spread":true,"position":{"start":{"line":6,"column":1},"end":{"line":6,"column":1}},"children":[{"type":"paragraph","children":[{"type":"link","url":"https://scikit-learn.org/stable/modules/generated/sklearn.preprocessing.StandardScaler.html#sklearn.preprocessing.StandardScaler","position":{"start":{"line":6,"column":1},"end":{"line":6,"column":1}},"children":[{"type":"text","value":"Scikit-learn’s StandardScaler Documentation","position":{"start":{"line":6,"column":1},"end":{"line":6,"column":1}},"key":"mZrgG58LSx"}],"urlSource":"https://scikit-learn.org/stable/modules/generated/sklearn.preprocessing.StandardScaler.html#sklearn.preprocessing.StandardScaler","key":"l2MenZY3ng"}],"key":"dTGcPVlMRw"}],"key":"e8dHMcwqpT"},{"type":"listItem","spread":true,"position":{"start":{"line":7,"column":1},"end":{"line":7,"column":1}},"children":[{"type":"paragraph","children":[{"type":"link","url":"https://towardsdatascience.com/what-and-why-behind-fit-transform-vs-transform-in-scikit-learn-78f915cf96fe","position":{"start":{"line":7,"column":1},"end":{"line":7,"column":1}},"children":[{"type":"text","value":"What and why behind fit_transform() and transform() in scikit-learn!","position":{"start":{"line":7,"column":1},"end":{"line":7,"column":1}},"key":"pNNFojIioS"}],"urlSource":"https://towardsdatascience.com/what-and-why-behind-fit-transform-vs-transform-in-scikit-learn-78f915cf96fe","key":"hzacqGgk7A"}],"key":"Dut6oOMGQ3"}],"key":"sfkMj1HV2n"},{"type":"listItem","spread":true,"position":{"start":{"line":8,"column":1},"end":{"line":9,"column":1}},"children":[{"type":"paragraph","children":[{"type":"link","url":"https://www.unidata.ucar.edu/blogs/news/entry/r-sup-2-sup-downsides","position":{"start":{"line":8,"column":1},"end":{"line":8,"column":1}},"children":[{"type":"text","value":"is\nR2: Downsides and Potential Pitfalls for ESS ML Predic","position":{"start":{"line":8,"column":1},"end":{"line":8,"column":1}},"key":"I1GALf8Jo4"}],"urlSource":"https://www.unidata.ucar.edu/blogs/news/entry/r-sup-2-sup-downsides","key":"CgRdNy2zLT"}],"key":"WbN3dJvgPD"}],"key":"OkWhIfagOG"},{"type":"listItem","spread":true,"position":{"start":{"line":10,"column":1},"end":{"line":10,"column":1}},"children":[{"type":"paragraph","children":[{"type":"link","url":"https://scikit-learn.org/stable/modules/tree.html","position":{"start":{"line":10,"column":1},"end":{"line":10,"column":1}},"children":[{"type":"text","value":"Scikit-learn’s Decision Trees","position":{"start":{"line":10,"column":1},"end":{"line":10,"column":1}},"key":"ntKLDWjiM7"}],"urlSource":"https://scikit-learn.org/stable/modules/tree.html","key":"GPYxph98Es"}],"key":"wpZMl3vcrN"}],"key":"J5zsIXN9rX"},{"type":"listItem","spread":true,"position":{"start":{"line":11,"column":1},"end":{"line":11,"column":1}},"children":[{"type":"paragraph","children":[{"type":"link","url":"https://www.youtube.com/watch?v=_L39rN6gz7Y","position":{"start":{"line":11,"column":1},"end":{"line":11,"column":1}},"children":[{"type":"text","value":"StatQuest video: Decision and Classification Trees, Clearly Explained!!!","position":{"start":{"line":11,"column":1},"end":{"line":11,"column":1}},"key":"b1Dq1Dwbyi"}],"urlSource":"https://www.youtube.com/watch?v=_L39rN6gz7Y","key":"x2ShMNy0SJ"},{"type":"text","value":"tion","position":{"start":{"line":11,"column":1},"end":{"line":11,"column":1}},"key":"TDHvRaeUrn"}],"key":"n8v7avNQ20"}],"key":"O8UJNwpQTv"}],"key":"Ijc2AYPTlq"}],"key":"Jwy9YtAECp"}],"key":"ZnZRHy05WH"},"references":{"cite":{"order":[],"data":{}}},"footer":{"navigation":{"prev":{"title":"How to Cite This Cookbook","url":"/notebooks/how-to-cite","group":"Preamble"}}},"domain":"http://localhost:3000"}